qr_detector/__init__.py
qr_detector/qr_detector.py
qr_detector_th-2.1.1.dist-info/METADATA
qr_detector_th-2.1.1.dist-info/WHEEL
qr_detector_th-2.1.1.dist-info/RECORD
