Metadata-Version: 2.4
Name: qr-detector-th
Version: 2.1.1
Summary: โมดูลตรวจจับ QR Code ด้วย OpenCV
Requires-Python: >=3.8
Requires-Dist: numpy
Requires-Dist: opencv-python
